[
    {
        "id":1,
        "name":"Tobit Eggerton",
        "gender":"Male",
        "specialisation":"Cardiologist",
        "qualifications":["ABC","DEF","GHI"],
        "availability":true,
        "duration":19,
        "fees":548,
        "location":"Kochi",
        "languages": ["Telugu"],
        "img":"https://robohash.org/similiqueimpeditquae.png?size=50x50&set=set1"
    },
    {
        "id":2,
        "name":"Birdie Dreini",
        "gender":"Female",
        "specialisation":"Psychiatrists",
        "qualifications":["GHI","JKL","MNO"],
        "availability":false,
        "duration":19,
        "fees":863,
        "location":"Kochi",
        "languages": ["English","Hindi"],
        "img":"https://robohash.org/fugasedaut.png?size=50x50&set=set1"
    },
    {
        "id":3,
        "name":"Zondra Battlestone",
        "gender":"Female",
        "specialisation":"Cardiologist",
        "availability":true,
        "qualifications":["ABC","DEF","MNO"],
        "duration":20,
        "fees":761,
        "location":"Trivandrum",
        "languages": ["English"],
        "img":"https://robohash.org/quianobisdolorem.png?size=50x50&set=set1"
    },
    {
        "id":4,
        "name":"Niko Seden",
        "gender":"Male",
        "specialisation":"Neurologist",
        "availability":false,
        "qualifications":["ABC","DEF","MNO"],
        "duration":19,
        "fees":1117,
        "location":"Kochi",
        "languages": ["English"],
        "img":"https://robohash.org/consecteturrationenihil.png?size=50x50&set=set1"
    },
    {
        "id":5,
        "name":"Pietro Cheers",
        "gender":"Male",
        "specialisation":"Psychiatrists",
        "qualifications":["ABC","DEF","GHI"],
        "availability":true,
        "duration":19,
        "fees":955,
        "location":"Trivandrum",
        "languages": ["English","Malayalam"],
        "img":"https://robohash.org/autoptioqui.png?size=50x50&set=set1"
    },
    {
        "id":6,
        "name":"Hogan Camden",
        "gender":"Male",
        "specialisation":"Cardiologist",
        "qualifications":"hcamden5@furl.net",
        "availability":false,
        "duration":20,
        "fees":829,
        "location":"Trivandrum",
        "languages": ["English","Malayalam"],
        "img":"https://robohash.org/laboriosamrerumest.png?size=50x50&set=set1"
    },
    {
        "id":7,
        "name":"Alexander Beagen",
        "gender":"Male",
        "specialisation":"Psychiatrists",
        "qualifications":["ABC","DEF","MNO"],
        "availability":true,
        "duration":20,
        "fees":550,
        "location":"Kochi",
        "languages": ["English","Malayalam","Hindi"],
        "img":"https://robohash.org/idlaborumdoloremque.png?size=50x50&set=set1"
    },
    {
        "id":8,
        "name":"Stafani Brithman",
        "gender":"Female",
        "specialisation":"Neurologist",
        "qualifications":["ABC","DEF","GHI"],
        "availability":false,
        "duration":20,
        "location":"Trivandrum",
        "languages": ["English","Tamil","Hindi"],
        "fees":808,"img":"https://robohash.org/idsolutanemo.png?size=50x50&set=set1"
    },
    {
        "id":9,
        "name":"Tonnie Romeril",
        "gender":"Male",
        "specialisation":"Cardiologist",
        "qualifications":["ABC","DEF","MNO"],
        "availability":false,
        "duration":19,
        "fees":985,
        "location":"Trivandrum",
        "languages": ["English","Malayalam","Tamil"],
        "img":"https://robohash.org/cumdolorumeveniet.png?size=50x50&set=set1"
    },
    {
        "id":10,
        "name":"Emeline Duffy",
        "gender":"Female",
        "specialisation":"Psychiatrists",
        "qualifications":["ABC","DEF","GHI"],
        "availability":true,
        "duration":19,
        "fees":944,
        "location":"Kochi",
        "languages": ["English","Malayalam","Tamil"],
        "img":"https://robohash.org/consequaturnemoea.png?size=50x50&set=set1"
    },
    {
        "id":11,
        "name":"Lina Memory",
        "gender":"Female",
        "specialisation":"Neurologist",
        "qualifications":["ABC","DEF","MNO"],
        "availability":true,
        "duration":20,
        "fees":621,
        "location":"Trivandrum",
        "languages": ["English","Malayalam","Tamil"],
        "img":"https://robohash.org/quodolorumbeatae.png?size=50x50&set=set1"
    },
    {
        "id":12,
        "name":"Emmeline Mowsdill",
        "gender":"Female",
        "specialisation":"ENT",
        "qualifications":["ABC","DEF","GHI"],
        "availability":false,
        "duration":19,
        "fees":1198,
        "location":"Trivandrum",
        "languages": ["English","Malayalam","Tamil"],
        "img":"https://robohash.org/autemarchitectosit.png?size=50x50&set=set1"
    },
    {
        "id":13,
        "name":"Pegeen Menlove",
        "gender":"Female",
        "specialisation":"Gynaecologist",
        "qualifications":["ABC","DEF","MNO"],
        "availability":true,
        "duration":19,
        "fees":861,
        "location":"Kochi",
        "languages": ["English","Malayalam","Hindi"],
        "img":"https://robohash.org/voluptasquaeeos.png?size=50x50&set=set1"
    },
    {
        "id":14,
        "name":"Simeon Fazzioli",
        "gender":"Male",
        "specialisation":"Psychiatrists",
        "qualifications":["ABC","DEF","GHI"],
        "availability":false,
        "duration":19,
        "fees":1194,
        "location":"Trivandrum",
        "languages": ["English","Malayalam","Hindi"],
        "img":"https://robohash.org/nostrumconsequaturrepudiandae.png?size=50x50&set=set1"
    },
    {
        "id":15,
        "name":"Patten Iacovuzzi",
        "gender":"Male",
        "specialisation":"Gynaecologist",
        "qualifications":["ABC","DEF","GHI"],
        "availability":true,
        "duration":20,
        "fees":519,
        "location":"Trivandrum",
        "languages": ["English","Malayalam","Hindi"],
        "img":"https://robohash.org/ipsamautemiste.png?size=50x50&set=set1"
    },
    {
        "id":16,
        "name":"Cindra Kipling",
        "gender":"Female",
        "specialisation":"ENT",
        "qualifications":["ABC","DEF","GHI"],
        "availability":true,
        "duration":19,
        "fees":768,
        "location":"Kochi",
        "languages": ["English","Tamil","Hindi"],
        "img":"https://robohash.org/doloretlibero.png?size=50x50&set=set1"
    },
    {
        "id":17,
        "name":"Nat Jorgensen",
        "gender":"Female",
        "specialisation":"Neurologist",
        "qualifications":["ABC","DEF","MNO"],
        "availability":true,
        "duration":20,
        "fees":587,
        "location":"Trivandrum",
        "languages": ["English","Tamil","Hindi"],
        "img":"https://robohash.org/doloremquedoloremrecusandae.png?size=50x50&set=set1"
    },
    {
        "id":18,
        "name":"Chrissie Tripp",
        "gender":"Male",
        "specialisation":"Gynaecologist",
        "qualifications":["ABC","DEF","GHI"],
        "availability":true,
        "duration":19,
        "fees":760,
        "location":"Trivandrum",
        "languages": ["English","Malayalam","Tamil","Hindi"],
        "img":"https://robohash.org/etillorepellat.png?size=50x50&set=set1"
    },
    {
        "id":19,
        "name":"Abbye Nuzzetti",
        "gender":"Female",
        "specialisation":"Neurologist",
        "qualifications":["ABC","DEF","GHI"],
        "availability":false,
        "duration":20,
        "fees":1028,
        "location":"Trivandrum",
        "languages": ["English","Tamil","Hindi"],
        "img":"https://robohash.org/perferendistemporibusaperiam.png?size=50x50&set=set1"
    },
    {
        "id":20,
        "name":"Felicle Smickle",
        "gender":"Female",
        "specialisation":"Neurologist",
        "qualifications":["ABC","DEF","MNO"],
        "availability":false,
        "duration":19,
        "fees":909,
        "location":"Trivandrum",
        "languages": ["English","Tamil","Hindi"],
        "img":"https://robohash.org/quibusdamautvoluptatem.png?size=50x50&set=set1"
    },
    {
        "id":21,
        "name":"Pren Felkin",
        "gender":"Male",
        "specialisation":"Neurologist",
        "qualifications":["ABC","DEF","GHI"],
        "availability":false,
        "duration":20,
        "fees":1138,
        "location":"Trivandrum",
        "languages": ["English","Tamil","Hindi"],
        "img":"https://robohash.org/possimuserrorquas.png?size=50x50&set=set1"
    },
    {
        "id":22,
        "name":"Eddy Mafham",
        "gender":"Female",
        "specialisation":"Gynaecologist",
        "qualifications":["ABC","DEF","GHI"],
        "availability":false,
        "duration":20,
        "location":"Trivandrum",
        "fees":1054,
        "languages": ["English","Malayalam"],
        "img":"https://robohash.org/iureutaut.png?size=50x50&set=set1"
    },
    {
        "id":23,
        "name":"Montgomery Sidary",
        "gender":"Male",
        "specialisation":"ENT",
        "qualifications":["ABC","DEF","GHI"],
        "availability":false,
        "duration":19,
        "fees":522,
        "location":"Trivandrum",
        "languages": ["English","Malayalam","Tamil"],
        "img":"https://robohash.org/dolorminusnecessitatibus.png?size=50x50&set=set1"
    },
    {
        "id":24,
        "name":"Brade Emblen",
        "gender":"Male",
        "specialisation":"ENT",
        "qualifications":["ABC","DEF","GHI"],
        "availability":true,
        "duration":20,
        "fees":1042,
        "location":"Trivandrum",
        "languages": ["English","Hindi"],
        "img":"https://robohash.org/uteosmolestias.png?size=50x50&set=set1"
    },
    {
        "id":25,
        "name":"Garrott Widdecombe",
        "gender":"Male",
        "specialisation":"Gynaecologist",
        "qualifications":["ABC","DEF","GHI"],
        "availability":true,
        "duration":19,
        "fees":668,
        "location":"Trivandrum",
        "languages": ["English","Malayalam"],
        "img":"https://robohash.org/indoloremet.png?size=50x50&set=set1"
    }
]    